{
  "indexes": [
    {
      "collectionGroup": "dog_logs",
      "queryScope": "COLLECTION",
      "fields": [
        { "fieldPath": "userId", "order": "ASCENDING" },
        { "fieldPath": "year", "order": "ASCENDING" },
        { "fieldPath": "loggedAt", "order": "DESCENDING" }
      ]
    },
    {
      "collectionGroup": "dog_logs",
      "queryScope": "COLLECTION",
      "fields": [
        { "fieldPath": "userId", "order": "ASCENDING" },
        { "fieldPath": "year", "order": "ASCENDING" },
        { "fieldPath": "loggedAt", "order": "ASCENDING" }
      ]
    },
    {
      "collectionGroup": "yearly_totals",
      "queryScope": "COLLECTION",
      "fields": [
        { "fieldPath": "year", "order": "ASCENDING" },
        { "fieldPath": "total", "order": "DESCENDING" },
        { "fieldPath": "mostRecentLoggedAt", "order": "DESCENDING" },
        { "fieldPath": "displayName", "order": "ASCENDING" }
      ]
    }
  ],
  "fieldOverrides": []
}

